cubicweb_tsfacets/__init__.py
cubicweb_tsfacets/__pkginfo__.py
cubicweb_tsfacets/ccplugin.py
cubicweb_tsfacets/entities.py
cubicweb_tsfacets/hooks.py
cubicweb_tsfacets/importer.py
cubicweb_tsfacets/schema.py
cubicweb_tsfacets/site_cubicweb.py
cubicweb_tsfacets/views.py
cubicweb_tsfacets/i18n/en.po
cubicweb_tsfacets/i18n/es.po
cubicweb_tsfacets/i18n/fr.po
cubicweb_tsfacets/migration/postcreate.py
cubicweb_tsfacets-0.7.1.dist-info/METADATA
cubicweb_tsfacets-0.7.1.dist-info/WHEEL
cubicweb_tsfacets-0.7.1.dist-info/entry_points.txt
cubicweb_tsfacets-0.7.1.dist-info/top_level.txt
cubicweb_tsfacets-0.7.1.dist-info/RECORD
