Metadata-Version: 2.1
Name: cubicweb-tsfacets
Version: 0.7.1
Summary: This cube implements facets using postgresql text search vectors.
Home-page: https://forge.extranet.logilab.fr/cubicweb/cubes/tsfacets
Author: LOGILAB S.A. (Paris, FRANCE)
Author-email: contact@logilab.fr
License: LGPL
Classifier: Environment :: Web Environment
Classifier: Framework :: CubicWeb
Classifier: Programming Language :: Python :: 3
Classifier: Programming Language :: JavaScript
Requires-Dist: cubicweb >=3.31.1
Requires-Dist: typing-extensions
